float_raster/LICENSE.md
float_raster/README.md
float_raster/__init__.py
float_raster/float_raster.py
float_raster/py.typed
float_raster-0.8.dist-info/METADATA
float_raster-0.8.dist-info/WHEEL
float_raster-0.8.dist-info/licenses/LICENSE.md
float_raster-0.8.dist-info/RECORD
