Metadata-Version: 2.3
Name: float_raster
Version: 0.8
Summary: High-precision anti-aliasing polygon rasterizer
Author-email: Jan Petykiewicz <jan@mpxd.net>
License: GNU Affero General Public License
License-File: LICENSE.md
Keywords: anti-alias,coverage,polygon,raster
Classifier: Development Status :: 4 - Beta
Classifier: Intended Audience :: Developers
Classifier: Intended Audience :: Information Technology
Classifier: Intended Audience :: Manufacturing
Classifier: Intended Audience :: Science/Research
Classifier: License :: OSI Approved :: GNU Affero General Public License v3
Classifier: Programming Language :: Python :: 3
Classifier: Topic :: Multimedia :: Graphics :: Graphics Conversion
Classifier: Topic :: Scientific/Engineering
Classifier: Topic :: Scientific/Engineering :: Electronic Design Automation (EDA)
Requires-Python: >=3.11
Requires-Dist: numpy>=1.26
Requires-Dist: scipy~=1.14
